{"answers":[{"acceptanceTime":"2023-01-20T12:37:27Z","answerContent":{"crowd-classifier":{"label":"Sometimes makes sense"}},"submissionTime":"2023-01-20T12:37:56Z","timeSpentInSeconds":29.0,"workerId":"public.us-east-1.A2Q7O0E83L1W74"},{"acceptanceTime":"2023-01-20T12:37:28Z","answerContent":{"crowd-classifier":{"label":"Does not make sense or Incorrect"}},"submissionTime":"2023-01-20T12:37:59Z","timeSpentInSeconds":31.0,"workerId":"public.us-east-1.A3174LRDWDKFLC"},{"acceptanceTime":"2023-01-20T12:37:28Z","answerContent":{"crowd-classifier":{"label":"First part and second part are not related! Or not enough information to judge"}},"submissionTime":"2023-01-20T12:38:29Z","timeSpentInSeconds":61.0,"workerId":"public.us-east-1.A8C5ZXLP2XBDS"}]}