{"answers":[{"acceptanceTime":"2023-01-18T19:50:25Z","answerContent":{"crowd-classifier":{"label":"Makes sense"}},"submissionTime":"2023-01-18T19:50:38Z","timeSpentInSeconds":13.0,"workerId":"public.us-east-1.A1BR5IBFDYQHR5"},{"acceptanceTime":"2023-01-18T19:50:25Z","answerContent":{"crowd-classifier":{"label":"Sometimes makes sense"}},"submissionTime":"2023-01-18T19:50:56Z","timeSpentInSeconds":31.0,"workerId":"public.us-east-1.A2P892H4FTO9R6"},{"acceptanceTime":"2023-01-18T19:50:26Z","answerContent":{"crowd-classifier":{"label":"Makes sense"}},"submissionTime":"2023-01-18T19:51:06Z","timeSpentInSeconds":40.0,"workerId":"public.us-east-1.A1BLDWE3JYO1O"}]}