{"answers":[{"acceptanceTime":"2023-01-13T04:46:28Z","answerContent":{"crowd-classifier":{"label":"Does not make sense or Incorrect"}},"submissionTime":"2023-01-13T04:46:54Z","timeSpentInSeconds":26.0,"workerId":"public.us-east-1.A15COXJDTSFIMT"},{"acceptanceTime":"2023-01-13T04:46:28Z","answerContent":{"crowd-classifier":{"label":"Makes sense"}},"submissionTime":"2023-01-13T04:47:32Z","timeSpentInSeconds":64.0,"workerId":"public.us-east-1.A2GWWF52EWDSEF"},{"acceptanceTime":"2023-01-13T04:46:28Z","answerContent":{"crowd-classifier":{"label":"Sometimes makes sense"}},"submissionTime":"2023-01-13T04:47:54Z","timeSpentInSeconds":86.0,"workerId":"public.us-east-1.A1OPEDEDKAKQMT"}]}