{"answers":[{"acceptanceTime":"2023-01-20T01:12:09Z","answerContent":{"crowd-classifier":{"label":"Does not make sense or Incorrect"}},"submissionTime":"2023-01-20T01:12:42Z","timeSpentInSeconds":33.0,"workerId":"public.us-east-1.A22LLU5METQ7CL"},{"acceptanceTime":"2023-01-20T01:12:09Z","answerContent":{"crowd-classifier":{"label":"Sometimes makes sense"}},"submissionTime":"2023-01-20T01:12:45Z","timeSpentInSeconds":36.0,"workerId":"public.us-east-1.ASEOEPDFLOU1K"},{"acceptanceTime":"2023-01-20T01:12:09Z","answerContent":{"crowd-classifier":{"label":"Sometimes makes sense"}},"submissionTime":"2023-01-20T01:15:34Z","timeSpentInSeconds":205.0,"workerId":"public.us-east-1.A2Z41S3WYUX2KP"}]}