[{"datasetObjectId":"40","dataObject":{"content":"PersonX never been to one. PersonX will be scared"},"annotations":[{"workerId":"private.us-east-1.c28c07bfa0547cc0","annotationData":{"content":"{\"crowd-classifier\":{\"label\":\"Makes sense\"}}"}}]},{"datasetObjectId":"29","dataObject":{"content":"PersonX sees PersonY\u0027s crush. PersonX will be happy."},"annotations":[{"workerId":"private.us-east-1.c28c07bfa0547cc0","annotationData":{"content":"{\"crowd-classifier\":{\"label\":\"Sometimes makes sense\"}}"}}]}]