{"answers":[{"acceptanceTime":"2023-01-20T12:27:05Z","answerContent":{"crowd-classifier":{"label":"Sometimes makes sense"}},"submissionTime":"2023-01-20T12:27:51Z","timeSpentInSeconds":46.0,"workerId":"public.us-east-1.AD42J3Y81IJMT"},{"acceptanceTime":"2023-01-20T12:27:05Z","answerContent":{"crowd-classifier":{"label":"Sometimes makes sense"}},"submissionTime":"2023-01-20T12:28:41Z","timeSpentInSeconds":96.0,"workerId":"public.us-east-1.A3CMNQJN07XEO9"},{"acceptanceTime":"2023-01-20T12:32:44Z","answerContent":{"crowd-classifier":{"label":"First part and second part are not related! Or not enough information to judge"}},"submissionTime":"2023-01-20T12:33:18Z","timeSpentInSeconds":34.0,"workerId":"public.us-east-1.A32WLG9ZR0YXUH"}]}