{"answers":[{"acceptanceTime":"2023-01-20T18:26:28Z","answerContent":{"crowd-classifier":{"label":"Does not make sense or Incorrect"}},"submissionTime":"2023-01-20T18:26:44Z","timeSpentInSeconds":16.0,"workerId":"public.us-east-1.A8C5ZXLP2XBDS"},{"acceptanceTime":"2023-01-20T18:26:29Z","answerContent":{"crowd-classifier":{"label":"Sometimes makes sense"}},"submissionTime":"2023-01-20T18:27:30Z","timeSpentInSeconds":61.0,"workerId":"public.us-east-1.A10ZBWUMUKMUQK"},{"acceptanceTime":"2023-01-20T18:26:29Z","answerContent":{"crowd-classifier":{"label":"Makes sense"}},"submissionTime":"2023-01-20T18:27:43Z","timeSpentInSeconds":74.0,"workerId":"public.us-east-1.A2PZWGSAUXOKKA"}]}