{"answers":[{"acceptanceTime":"2023-01-20T00:49:30Z","answerContent":{"crowd-classifier":{"label":"Makes sense"}},"submissionTime":"2023-01-20T00:49:49Z","timeSpentInSeconds":19.0,"workerId":"public.us-east-1.A2JG4MXWTU2Y2O"},{"acceptanceTime":"2023-01-20T00:49:33Z","answerContent":{"crowd-classifier":{"label":"Sometimes makes sense"}},"submissionTime":"2023-01-20T00:50:02Z","timeSpentInSeconds":29.0,"workerId":"public.us-east-1.A20NNUVDL65RVV"},{"acceptanceTime":"2023-01-20T00:49:33Z","answerContent":{"crowd-classifier":{"label":"Makes sense"}},"submissionTime":"2023-01-20T00:50:29Z","timeSpentInSeconds":56.0,"workerId":"public.us-east-1.A18D69774I4CP8"}]}