{"answers":[{"acceptanceTime":"2023-01-18T19:34:34Z","answerContent":{"crowd-classifier":{"label":"Does not make sense or Incorrect"}},"submissionTime":"2023-01-18T19:34:47Z","timeSpentInSeconds":13.0,"workerId":"public.us-east-1.A1EHJUEVUIBE93"},{"acceptanceTime":"2023-01-18T19:34:34Z","answerContent":{"crowd-classifier":{"label":"Sometimes makes sense"}},"submissionTime":"2023-01-18T19:35:04Z","timeSpentInSeconds":30.0,"workerId":"public.us-east-1.A3AWARGS34RHZY"},{"acceptanceTime":"2023-01-18T19:34:33Z","answerContent":{"crowd-classifier":{"label":"Makes sense"}},"submissionTime":"2023-01-18T19:36:51Z","timeSpentInSeconds":138.0,"workerId":"public.us-east-1.A2404K01AK5XDB"}]}