{"answers":[{"acceptanceTime":"2023-01-20T16:26:54Z","answerContent":{"crowd-classifier":{"label":"Makes sense"}},"submissionTime":"2023-01-20T16:27:15Z","timeSpentInSeconds":21.0,"workerId":"public.us-east-1.A33PGKLIVHK1EO"},{"acceptanceTime":"2023-01-20T16:26:53Z","answerContent":{"crowd-classifier":{"label":"Sometimes makes sense"}},"submissionTime":"2023-01-20T16:27:28Z","timeSpentInSeconds":35.0,"workerId":"public.us-east-1.A2JG4MXWTU2Y2O"},{"acceptanceTime":"2023-01-20T16:32:44Z","answerContent":{"crowd-classifier":{"label":"Sometimes makes sense"}},"submissionTime":"2023-01-20T16:34:11Z","timeSpentInSeconds":87.0,"workerId":"public.us-east-1.A1B8Z8UIYUNFOI"}]}