{"answers":[{"acceptanceTime":"2023-01-20T12:43:21Z","answerContent":{"crowd-classifier":{"label":"First part and second part are not related! Or not enough information to judge"}},"submissionTime":"2023-01-20T12:43:34Z","timeSpentInSeconds":13.0,"workerId":"public.us-east-1.A32WLG9ZR0YXUH"},{"acceptanceTime":"2023-01-20T12:43:21Z","answerContent":{"crowd-classifier":{"label":"Does not make sense or Incorrect"}},"submissionTime":"2023-01-20T12:44:04Z","timeSpentInSeconds":43.0,"workerId":"public.us-east-1.A2FAIDFRBYVPGO"},{"acceptanceTime":"2023-01-20T12:48:34Z","answerContent":{"crowd-classifier":{"label":"Sometimes makes sense"}},"submissionTime":"2023-01-20T12:50:48Z","timeSpentInSeconds":134.0,"workerId":"public.us-east-1.A23D23Z5FEFF7J"}]}