{"answers":[{"acceptanceTime":"2023-01-20T01:05:54Z","answerContent":{"crowd-classifier":{"label":"Sometimes makes sense"}},"submissionTime":"2023-01-20T01:06:20Z","timeSpentInSeconds":26.0,"workerId":"public.us-east-1.A3HE8B51AK8TET"},{"acceptanceTime":"2023-01-20T01:05:55Z","answerContent":{"crowd-classifier":{"label":"Does not make sense or Incorrect"}},"submissionTime":"2023-01-20T01:06:26Z","timeSpentInSeconds":31.0,"workerId":"public.us-east-1.A4WEEFCKZ9AG4"},{"acceptanceTime":"2023-01-20T01:11:08Z","answerContent":{"crowd-classifier":{"label":"Does not make sense or Incorrect"}},"submissionTime":"2023-01-20T01:13:02Z","timeSpentInSeconds":114.0,"workerId":"public.us-east-1.A3ETIB7Q14P06Q"}]}