{"answers":[{"acceptanceTime":"2023-01-20T12:27:03Z","answerContent":{"crowd-classifier":{"label":"Does not make sense or Incorrect"}},"submissionTime":"2023-01-20T12:28:00Z","timeSpentInSeconds":57.0,"workerId":"public.us-east-1.A1SCF3L6LTFQHF"},{"acceptanceTime":"2023-01-20T12:27:00Z","answerContent":{"crowd-classifier":{"label":"Sometimes makes sense"}},"submissionTime":"2023-01-20T12:28:32Z","timeSpentInSeconds":92.0,"workerId":"public.us-east-1.A3HAG4AFOE0P7H"},{"acceptanceTime":"2023-01-20T12:32:44Z","answerContent":{"crowd-classifier":{"label":"Makes sense"}},"submissionTime":"2023-01-20T12:33:01Z","timeSpentInSeconds":17.0,"workerId":"public.us-east-1.A3V17JX798FUS3"}]}