{"answers":[{"acceptanceTime":"2023-01-20T05:31:09Z","answerContent":{"crowd-classifier":{"label":"Sometimes makes sense"}},"submissionTime":"2023-01-20T05:31:35Z","timeSpentInSeconds":26.0,"workerId":"public.us-east-1.A3RAQ8SWUHMOMD"},{"acceptanceTime":"2023-01-20T05:31:09Z","answerContent":{"crowd-classifier":{"label":"Does not make sense or Incorrect"}},"submissionTime":"2023-01-20T05:31:45Z","timeSpentInSeconds":36.0,"workerId":"public.us-east-1.A3IOXSHHNWDUD4"},{"acceptanceTime":"2023-01-20T05:31:09Z","answerContent":{"crowd-classifier":{"label":"Sometimes makes sense"}},"submissionTime":"2023-01-20T05:32:19Z","timeSpentInSeconds":70.0,"workerId":"public.us-east-1.AIB8QLWO1TVS"}]}