{"answers":[{"acceptanceTime":"2023-01-20T18:18:51Z","answerContent":{"crowd-classifier":{"label":"Makes sense"}},"submissionTime":"2023-01-20T18:19:02Z","timeSpentInSeconds":11.0,"workerId":"public.us-east-1.A2PZWGSAUXOKKA"},{"acceptanceTime":"2023-01-20T18:18:51Z","answerContent":{"crowd-classifier":{"label":"Makes sense"}},"submissionTime":"2023-01-20T18:19:03Z","timeSpentInSeconds":12.0,"workerId":"public.us-east-1.A27XT8JVY36LK"},{"acceptanceTime":"2023-01-20T18:18:50Z","answerContent":{"crowd-classifier":{"label":"Unfamiliar to me to judge"}},"submissionTime":"2023-01-20T18:19:27Z","timeSpentInSeconds":37.0,"workerId":"public.us-east-1.AH3GTA1337UGW"}]}