{"answers":[{"acceptanceTime":"2023-01-20T00:49:44Z","answerContent":{"crowd-classifier":{"label":"Sometimes makes sense"}},"submissionTime":"2023-01-20T00:49:59Z","timeSpentInSeconds":15.0,"workerId":"public.us-east-1.A1DKMOR2ZJHS2X"},{"acceptanceTime":"2023-01-20T00:49:49Z","answerContent":{"crowd-classifier":{"label":"Makes sense"}},"submissionTime":"2023-01-20T00:50:09Z","timeSpentInSeconds":20.0,"workerId":"public.us-east-1.AF642VCALD1MS"},{"acceptanceTime":"2023-01-20T00:49:47Z","answerContent":{"crowd-classifier":{"label":"Makes sense"}},"submissionTime":"2023-01-20T00:50:17Z","timeSpentInSeconds":30.0,"workerId":"public.us-east-1.A2JG4MXWTU2Y2O"}]}