{"answers":[{"acceptanceTime":"2023-01-18T19:29:03Z","answerContent":{"crowd-classifier":{"label":"First part and second part are not related! Or not enough information to judge"}},"submissionTime":"2023-01-18T19:29:29Z","timeSpentInSeconds":26.0,"workerId":"public.us-east-1.A1JCI4LMNRO2DL"},{"acceptanceTime":"2023-01-18T19:29:04Z","answerContent":{"crowd-classifier":{"label":"Makes sense"}},"submissionTime":"2023-01-18T19:31:26Z","timeSpentInSeconds":142.0,"workerId":"public.us-east-1.A2GXEVBJ69CD8Z"},{"acceptanceTime":"2023-01-18T19:29:03Z","answerContent":{"crowd-classifier":{"label":"Makes sense"}},"submissionTime":"2023-01-18T19:31:40Z","timeSpentInSeconds":157.0,"workerId":"public.us-east-1.AY43DZXXANP6L"}]}