{"answers":[{"acceptanceTime":"2023-01-19T22:25:03Z","answerContent":{"crowd-classifier":{"label":"First part and second part are not related! Or not enough information to judge"}},"submissionTime":"2023-01-19T22:26:18Z","timeSpentInSeconds":75.0,"workerId":"public.us-east-1.A2QDBS1CB2J9J1"},{"acceptanceTime":"2023-01-19T22:25:00Z","answerContent":{"crowd-classifier":{"label":"Sometimes makes sense"}},"submissionTime":"2023-01-19T22:26:41Z","timeSpentInSeconds":101.0,"workerId":"public.us-east-1.A2TAWIW9QRC5M7"},{"acceptanceTime":"2023-01-19T22:25:03Z","answerContent":{"crowd-classifier":{"label":"First part and second part are not related! Or not enough information to judge"}},"submissionTime":"2023-01-19T22:27:00Z","timeSpentInSeconds":117.0,"workerId":"public.us-east-1.A3ETIB7Q14P06Q"}]}