{"answers":[{"acceptanceTime":"2023-01-12T22:49:04Z","answerContent":{"crowd-classifier":{"label":"Makes sense"}},"submissionTime":"2023-01-12T22:49:33Z","timeSpentInSeconds":29.0,"workerId":"public.us-east-1.AD3VY2BAFL01N"},{"acceptanceTime":"2023-01-12T22:49:03Z","answerContent":{"crowd-classifier":{"label":"Unfamiliar to me to judge"}},"submissionTime":"2023-01-12T22:51:08Z","timeSpentInSeconds":125.0,"workerId":"public.us-east-1.A1ALRR1J25RBYX"},{"acceptanceTime":"2023-01-12T22:54:42Z","answerContent":{"crowd-classifier":{"label":"Sometimes makes sense"}},"submissionTime":"2023-01-12T22:54:56Z","timeSpentInSeconds":14.0,"workerId":"public.us-east-1.A35TF71Q0XO0PH"}]}