{"answers":[{"acceptanceTime":"2023-01-18T19:37:56Z","answerContent":{"crowd-classifier":{"label":"Makes sense"}},"submissionTime":"2023-01-18T19:38:31Z","timeSpentInSeconds":35.0,"workerId":"public.us-east-1.A30ISYG8LD4NT3"},{"acceptanceTime":"2023-01-18T19:37:56Z","answerContent":{"crowd-classifier":{"label":"Sometimes makes sense"}},"submissionTime":"2023-01-18T19:39:14Z","timeSpentInSeconds":78.0,"workerId":"public.us-east-1.A2P5ZLIYPQ6MFG"},{"acceptanceTime":"2023-01-18T19:43:16Z","answerContent":{"crowd-classifier":{"label":"Makes sense"}},"submissionTime":"2023-01-18T19:46:19Z","timeSpentInSeconds":183.0,"workerId":"public.us-east-1.AY43DZXXANP6L"}]}