{"answers":[{"acceptanceTime":"2023-01-13T04:59:12Z","answerContent":{"crowd-classifier":{"label":"Does not make sense or Incorrect"}},"submissionTime":"2023-01-13T04:59:43Z","timeSpentInSeconds":31.0,"workerId":"public.us-east-1.A1O71XNV203T5P"},{"acceptanceTime":"2023-01-13T04:59:12Z","answerContent":{"crowd-classifier":{"label":"Does not make sense or Incorrect"}},"submissionTime":"2023-01-13T05:00:35Z","timeSpentInSeconds":83.0,"workerId":"public.us-east-1.A15ZOCRKKXZFMP"},{"acceptanceTime":"2023-01-13T05:04:20Z","answerContent":{"crowd-classifier":{"label":"Sometimes makes sense"}},"submissionTime":"2023-01-13T05:05:37Z","timeSpentInSeconds":77.0,"workerId":"public.us-east-1.A2SJ2473KT2BYQ"}]}