{"answers":[{"acceptanceTime":"2023-01-20T18:29:14Z","answerContent":{"crowd-classifier":{"label":"First part and second part are not related! Or not enough information to judge"}},"submissionTime":"2023-01-20T18:29:54Z","timeSpentInSeconds":40.0,"workerId":"public.us-east-1.A24CRX9IWE2V4X"},{"acceptanceTime":"2023-01-20T18:29:14Z","answerContent":{"crowd-classifier":{"label":"Does not make sense or Incorrect"}},"submissionTime":"2023-01-20T18:30:04Z","timeSpentInSeconds":50.0,"workerId":"public.us-east-1.AI63RWXMG3QNB"},{"acceptanceTime":"2023-01-20T18:34:15Z","answerContent":{"crowd-classifier":{"label":"Sometimes makes sense"}},"submissionTime":"2023-01-20T18:35:14Z","timeSpentInSeconds":59.0,"workerId":"public.us-east-1.A28ZADY8SPKMHX"}]}